XRootD/__init__.py
XRootD/client/__init__.py
XRootD/client/_version.py
XRootD/client/copyprocess.py
XRootD/client/env.py
XRootD/client/file.py
XRootD/client/filesystem.py
XRootD/client/finalize.py
XRootD/client/flags.py
XRootD/client/glob_funcs.py
XRootD/client/responses.py
XRootD/client/url.py
XRootD/client/utils.py
pyxrootd/__init__.py
pyxrootd/client.cpython-311-darwin.so
pyxrootd/libXrdAppUtils.2.0.0.dylib
pyxrootd/libXrdAppUtils.2.dylib
pyxrootd/libXrdAppUtils.dylib
pyxrootd/libXrdCl.3.0.0.dylib
pyxrootd/libXrdCl.3.dylib
pyxrootd/libXrdCl.dylib
pyxrootd/libXrdClHttp-5.so
pyxrootd/libXrdClProxyPlugin-5.so
pyxrootd/libXrdClRecorder-5.so
pyxrootd/libXrdCrypto.2.0.0.dylib
pyxrootd/libXrdCrypto.2.dylib
pyxrootd/libXrdCrypto.dylib
pyxrootd/libXrdCryptoLite.2.0.0.dylib
pyxrootd/libXrdCryptoLite.2.dylib
pyxrootd/libXrdCryptoLite.dylib
pyxrootd/libXrdCryptossl-5.so
pyxrootd/libXrdPosix.3.0.0.dylib
pyxrootd/libXrdPosix.3.dylib
pyxrootd/libXrdPosix.dylib
pyxrootd/libXrdPosixPreload.2.0.0.dylib
pyxrootd/libXrdPosixPreload.2.dylib
pyxrootd/libXrdPosixPreload.dylib
pyxrootd/libXrdSec-5.so
pyxrootd/libXrdSecProt-5.so
pyxrootd/libXrdSecgsi-5.so
pyxrootd/libXrdSecgsiAUTHZVO-5.so
pyxrootd/libXrdSecgsiGMAPDN-5.so
pyxrootd/libXrdSeckrb5-5.so
pyxrootd/libXrdSecpwd-5.so
pyxrootd/libXrdSecsss-5.so
pyxrootd/libXrdSecunix-5.so
pyxrootd/libXrdSecztn-5.so
pyxrootd/libXrdUtils.3.0.0.dylib
pyxrootd/libXrdUtils.3.dylib
pyxrootd/libXrdUtils.dylib
pyxrootd/libXrdXml.3.0.0.dylib
pyxrootd/libXrdXml.3.dylib
pyxrootd/libXrdXml.dylib
xrootd-5.6.0.dist-info/COPYING
xrootd-5.6.0.dist-info/COPYING.BSD
xrootd-5.6.0.dist-info/COPYING.LGPL
xrootd-5.6.0.dist-info/LICENSE
xrootd-5.6.0.dist-info/METADATA
xrootd-5.6.0.dist-info/WHEEL
xrootd-5.6.0.dist-info/top_level.txt
xrootd-5.6.0.dist-info/RECORD
